device_drama/classes/base_plugin.py
device_drama/classes/config.py
device_drama/classes/logger.py
device_drama/classes/plugin_validator.py
device_drama/main.py
device_drama/misc.py
device_drama/plugins/01_main_hardware/01_mobo_info.py
device_drama/plugins/01_main_hardware/02_cpu_info.py
device_drama/plugins/01_main_hardware/03_gpu_info.py
device_drama/plugins/01_main_hardware/04_ram_info.py
device_drama/plugins/02_disks/01_disks_info.py
device_drama/plugins/03_monitors/01_monitors_info.py
device_drama/plugins/04_operating_system/01_os_info.py
device_drama/plugins/05_applications/01_shell_info.py
device_drama/plugins/05_applications/02_wm_info.py
device_drama/plugins/05_applications/03_terminal_info.py
device_drama-24.5.13.dist-info/METADATA
device_drama-24.5.13.dist-info/WHEEL
device_drama-24.5.13.dist-info/entry_points.txt
device_drama-24.5.13.dist-info/RECORD
